AxCat/__init__.py
AxCat/Github/__init__.py
AxCat/Github/message.py
zzy_AxCat-0.1.dist-info/METADATA
zzy_AxCat-0.1.dist-info/WHEEL
zzy_AxCat-0.1.dist-info/top_level.txt
zzy_AxCat-0.1.dist-info/RECORD
