Metadata-Version: 2.1
Name: zzy-AxCat
Version: 0.1
Summary: 曾子毅
Author: zzy
License: UNKNOWN
Platform: UNKNOWN
